pymodaq_plugins_raspberry/__init__.py
pymodaq_plugins_raspberry/utils.py
pymodaq_plugins_raspberry/daq_move_plugins/__init__.py
pymodaq_plugins_raspberry/daq_viewer_plugins/__init__.py
pymodaq_plugins_raspberry/daq_viewer_plugins/plugins_0D/__init__.py
pymodaq_plugins_raspberry/daq_viewer_plugins/plugins_1D/__init__.py
pymodaq_plugins_raspberry/daq_viewer_plugins/plugins_2D/__init__.py
pymodaq_plugins_raspberry/daq_viewer_plugins/plugins_2D/daq_2Dviewer_PiCamera.py
pymodaq_plugins_raspberry/daq_viewer_plugins/plugins_ND/__init__.py
pymodaq_plugins_raspberry/exporters/__init__.py
pymodaq_plugins_raspberry/extensions/__init__.py
pymodaq_plugins_raspberry/hardware/__init__.py
pymodaq_plugins_raspberry/models/__init__.py
pymodaq_plugins_raspberry/resources/VERSION
pymodaq_plugins_raspberry/resources/__init__.py
pymodaq_plugins_raspberry/resources/config_template.toml
pymodaq_plugins_raspberry/scanners/__init__.py
pymodaq_plugins_raspberry-0.0.2.dist-info/LICENSE
pymodaq_plugins_raspberry-0.0.2.dist-info/METADATA
pymodaq_plugins_raspberry-0.0.2.dist-info/WHEEL
pymodaq_plugins_raspberry-0.0.2.dist-info/entry_points.txt
pymodaq_plugins_raspberry-0.0.2.dist-info/top_level.txt
pymodaq_plugins_raspberry-0.0.2.dist-info/RECORD
